hattie/__init__.py
hattie/database.py
hattie/dbmanager.py
hattie/hattie.py
hattie/legistar.py
hattie/manager.py
hattie/tagger.py
hattie/util.py
hattie/collector/__init__.py
hattie/collector/action.py
hattie/collector/base.py
hattie/collector/departments.py
hattie/collector/item.py
hattie/collector/main.py
hattie/collector/meeting.py
hattie/collector/people.py
hattie/collector/rss.py
hattie/managers/__init__.py
hattie/managers/base.py
hattie/managers/basic.py
hattie/managers/main.py
hattie/managers/util.py
hattie-0.2.23.dist-info/AUTHORS.rst
hattie-0.2.23.dist-info/LICENSE
hattie-0.2.23.dist-info/METADATA
hattie-0.2.23.dist-info/WHEEL
hattie-0.2.23.dist-info/top_level.txt
hattie-0.2.23.dist-info/RECORD
