Metadata-Version: 2.1
Name: hattie
Version: 0.2.23
Summary: municipal legislation
Home-page: https://github.com/umeboshi2/hattie
Author: Joseph Rawson
Author-email: joseph.rawson.works@gmail.com
License: UNLICENSED
Keywords: hattie
Platform: UNKNOWN
Classifier: Development Status :: 2 - Pre-Alpha
Classifier: Intended Audience :: Developers
Classifier: License :: Public Domain
Classifier: Natural Language :: English
Classifier: Programming Language :: Python :: 2
Classifier: Programming Language :: Python :: 2.7
Classifier: Programming Language :: Python :: 3
Classifier: Programming Language :: Python :: 3.4
Classifier: Programming Language :: Python :: 3.5
Classifier: Programming Language :: Python :: 3.6
Requires-Dist: feedparser
Requires-Dist: requests
Requires-Dist: robobrowser
Requires-Dist: transaction
